roscenes/__init__.py
roscenes/check.py
roscenes/info.py
roscenes/main.py
roscenes/record2bag.py
roscenes/common/calib.py
roscenes/common/check.py
roscenes/common/constant.py
roscenes/common/data_config.py
roscenes/common/fix.py
roscenes/common/nuscenes_check.py
roscenes/common/scene_check.py
roscenes/common/utils.py
roscenes/decompress/__init__.py
roscenes/decompress/decompress.py
roscenes/decompress/main.py
roscenes/decompress/utils.py
roscenes/export/__init__.py
roscenes/export/export copy.py
roscenes/export/export.py
roscenes/export/main.py
roscenes/export/sus.py
roscenes/export/utils.py
roscenes/load/__init__.py
roscenes/load/load.py
roscenes/load/main.py
roscenes/load/sus copy.py
roscenes/load/sus.py
roscenes/load/utils.py
roscenes/merge/__init__.py
roscenes/merge/main.py
roscenes/merge/merge.py
roscenes/merge/merge_cml.py
roscenes/nuscenes/__init__.py
roscenes/nuscenes/annotation.py
roscenes/nuscenes/extraction.py
roscenes/nuscenes/nuscenes_info.py
roscenes/nuscenes/nuscenes_objects.py
roscenes/nuscenes/rule.py
roscenes/nuscenes/taxonomy.py
roscenes/nuscenes/utils.py
roscenes/nuscenes/vehicle.py
roscenes/slice/__init__.py
roscenes/slice/base copy.py
roscenes/slice/base.py
roscenes/slice/main.py
roscenes/slice/slice.py
roscenes/slice/utils.py
rosbag2nuscenes-0.0.1.dist-info/LICENSE
rosbag2nuscenes-0.0.1.dist-info/METADATA
rosbag2nuscenes-0.0.1.dist-info/WHEEL
rosbag2nuscenes-0.0.1.dist-info/entry_points.txt
rosbag2nuscenes-0.0.1.dist-info/top_level.txt
rosbag2nuscenes-0.0.1.dist-info/RECORD
